retinex/VERSION
retinex/__init__.py
retinex/retinex.py
retinex-0.0.1.dist-info/LICENSE
retinex-0.0.1.dist-info/METADATA
retinex-0.0.1.dist-info/WHEEL
retinex-0.0.1.dist-info/top_level.txt
retinex-0.0.1.dist-info/RECORD
