Metadata-Version: 2.1
Name: retinex
Version: 0.0.1
Summary: Retinex algorithms for image enhancement
Home-page: https://github.com/gui-miotto/retinex/
Author: Guilherme Miotto
License-File: LICENSE
Requires-Dist: scikit-image >=0.20
Requires-Dist: numpy
Provides-Extra: test
